rtbdata/__init__.py
rtbdata/__pycache__/__init__.cpython-310.pyc
rtbdata/__pycache__/__init__.cpython-311.pyc
rtbdata/__pycache__/__init__.cpython-38.pyc
rtbdata/__pycache__/__init__.cpython-39.pyc
rtbdata/data/gimbal-ring1.stl
rtbdata/data/gimbal-ring2.stl
rtbdata/data/gimbal-ring3.stl
rtbdata/data/greycar.png
rtbdata/data/hershey.json
rtbdata/data/house.mat
rtbdata/data/killian-small.toro
rtbdata/data/killian.g2o.zip
rtbdata/data/map1.mat
rtbdata/data/pg1.g2o
rtbdata/data/piano.png
rtbdata/data/places.json
rtbdata/data/queensland.json
rtbdata/data/redcar.png
rtbdata/data/routes.json
rtbdata/data/spitfire_assy-gear_up.stl
rtbdata/data/test.mat
rtbdata/data/test.urdf
rtbdata/data/test-mesh/walle2.ply
rtbdata/data/test-mesh/walle2.tex
rtbdata/data/test-mesh/walle2.u3d
rtbdata/meshes/README.md
rtbdata/meshes/ABB/IRB140/link0.stl
rtbdata/meshes/ABB/IRB140/link1.stl
rtbdata/meshes/ABB/IRB140/link2.stl
rtbdata/meshes/ABB/IRB140/link3.stl
rtbdata/meshes/ABB/IRB140/link4.stl
rtbdata/meshes/ABB/IRB140/link5.stl
rtbdata/meshes/ABB/IRB140/link6.stl
rtbdata/meshes/FRANKA-EMIKA/Panda/finger.stl
rtbdata/meshes/FRANKA-EMIKA/Panda/hand.stl
rtbdata/meshes/FRANKA-EMIKA/Panda/link0.stl
rtbdata/meshes/FRANKA-EMIKA/Panda/link0_original.stl
rtbdata/meshes/FRANKA-EMIKA/Panda/link1.stl
rtbdata/meshes/FRANKA-EMIKA/Panda/link1_original.stl
rtbdata/meshes/FRANKA-EMIKA/Panda/link2.stl
rtbdata/meshes/FRANKA-EMIKA/Panda/link2_original.stl
rtbdata/meshes/FRANKA-EMIKA/Panda/link3.stl
rtbdata/meshes/FRANKA-EMIKA/Panda/link3_original.stl
rtbdata/meshes/FRANKA-EMIKA/Panda/link4.stl
rtbdata/meshes/FRANKA-EMIKA/Panda/link4_original.stl
rtbdata/meshes/FRANKA-EMIKA/Panda/link5.stl
rtbdata/meshes/FRANKA-EMIKA/Panda/link5_original.stl
rtbdata/meshes/FRANKA-EMIKA/Panda/link6.stl
rtbdata/meshes/FRANKA-EMIKA/Panda/link6_original.stl
rtbdata/meshes/FRANKA-EMIKA/Panda/link7.stl
rtbdata/meshes/FRANKA-EMIKA/Panda/link7_original.stl
rtbdata/meshes/KUKA/KR5_arc/link0.stl
rtbdata/meshes/KUKA/KR5_arc/link1.stl
neura_rtb_data-0.0.1.dist-info/METADATA
neura_rtb_data-0.0.1.dist-info/WHEEL
neura_rtb_data-0.0.1.dist-info/top_level.txt
neura_rtb_data-0.0.1.dist-info/RECORD
