Metadata-Version: 2.1
Name: neura-rtb-data
Version: 0.0.1
Summary: Data files for the Robotics Toolbox for Python.
Home-page: https://github.com/JTem/neura-roboticstoolbox
Author: Jens Temminghoff
Author-email: jens.temminghoff@neura-robotics.com
Project-URL: Source, https://github.com/JTem/neura-roboticstoolbox
Keywords: python robotics
Classifier: Development Status :: 5 - Production/Stable
Classifier: Intended Audience :: Developers
Classifier: License :: OSI Approved :: MIT License
Classifier: Programming Language :: Python :: 3 :: Only
